{"version":2,"kind":"Article","sha256":"bfb33abc4c2f68b43bc428f3eb831d49525357594539ae00bb8e6562fff14b15","slug":"index","location":"/README.md","dependencies":[],"frontmatter":{"title":"CMIP6 Cookbook","content_includes_title":false,"authors":[{"nameParsed":{"literal":"Ryan Abernathey","given":"Ryan","family":"Abernathey"},"name":"Ryan Abernathey","id":"contributors-myst-generated-uid-0"},{"nameParsed":{"literal":"Henri Drake","given":"Henri","family":"Drake"},"name":"Henri Drake","id":"contributors-myst-generated-uid-1"},{"nameParsed":{"literal":"Robert Ford","given":"Robert","family":"Ford"},"name":"Robert Ford","id":"contributors-myst-generated-uid-2"},{"nameParsed":{"literal":"Max Grover","given":"Max","family":"Grover"},"name":"Max Grover","id":"contributors-myst-generated-uid-3"}],"open_access":true,"license":{"content":{"id":"CC-BY-4.0","url":"https://creativecommons.org/licenses/by/4.0/","name":"Creative Commons Attribution 4.0 International","free":true,"CC":true},"code":{"id":"Apache-2.0","url":"https://opensource.org/licenses/Apache-2.0","name":"Apache License 2.0","free":true,"osi":true}},"github":"https://github.com/projectpythia/cmip6-cookbook","copyright":"2024","affiliations":[{"id":"UAlbany","name":"University at Albany (SUNY)","department":"Atmospheric and Environmental Sciences","url":"https://www.albany.edu/daes"},{"id":"CISL","name":"NSF National Center for Atmospheric Research","department":"Computational and Information Systems Lab","url":"https://www.cisl.ucar.edu"},{"id":"Unidata","name":"NSF Unidata","url":"https://www.unidata.ucar.edu"},{"id":"Argonne","name":"Argonne National Laboratory","department":"Environmental Science Division","url":"https://www.anl.gov/evs"},{"id":"CarbonPlan","name":"CarbonPlan","url":"https://carbonplan.org"},{"id":"NVIDIA","name":"NVIDIA Corporation","url":"https://www.nvidia.com/"}],"source_url":"https://github.com/projectpythia/cmip6-cookbook/blob/main/README.md","edit_url":"https://github.com/projectpythia/cmip6-cookbook/edit/main/README.md","thumbnail":"/cmip6-cookbook/build/cmip6-logo-4ebfe93797e4437a1f1e18dd12f1616f.webp","exports":[{"format":"md","filename":"README.md","url":"/cmip6-cookbook/build/README-69a5348af56af6fbecb6d88d71a901b9.md"}]},"mdast":{"type":"root","children":[{"type":"block","children":[{"type":"paragraph","position":{"start":{"line":3,"column":1},"end":{"line":3,"column":1}},"children":[{"type":"image","url":"/cmip6-cookbook/build/cmip6-logo-4ebfe93797e4437a1f1e18dd12f1616f.webp","alt":"CMIP6 logo","width":500,"key":"Zs0ZFjszhf","urlSource":"notebooks/images/cmip6-logo.webp"}],"key":"OrSgpoe8Sh"},{"type":"paragraph","position":{"start":{"line":5,"column":1},"end":{"line":7,"column":1}},"children":[{"type":"link","url":"https://github.com/ProjectPythia/cmip6-cookbook/actions/workflows/nightly-build.yaml","position":{"start":{"line":5,"column":1},"end":{"line":5,"column":1}},"children":[{"type":"image","url":"/cmip6-cookbook/build/498a74334e2e01db5a708d61fb04f639.svg","alt":"nightly-build","position":{"start":{"line":5,"column":1},"end":{"line":5,"column":1}},"key":"iH5R974DkF","urlSource":"https://github.com/ProjectPythia/cmip6-cookbook/actions/workflows/nightly-build.yaml/badge.svg"}],"urlSource":"https://github.com/ProjectPythia/cmip6-cookbook/actions/workflows/nightly-build.yaml","error":true,"key":"wozqy4QyNt"},{"type":"text","value":"\n","position":{"start":{"line":5,"column":1},"end":{"line":5,"column":1}},"key":"nvr9zQnVCm"},{"type":"link","url":"https://binder.projectpythia.org/v2/gh/ProjectPythia/cmip6-cookbook.git/main","position":{"start":{"line":5,"column":1},"end":{"line":5,"column":1}},"children":[{"type":"image","url":"/cmip6-cookbook/build/31e3f387ea168934ca949c27e9927ea4.svg","alt":"Binder","position":{"start":{"line":5,"column":1},"end":{"line":5,"column":1}},"key":"WlOJmYVvQN","urlSource":"https://binder.projectpythia.org/badge_logo.svg"}],"urlSource":"https://binder.projectpythia.org/v2/gh/ProjectPythia/cmip6-cookbook.git/main","key":"ztk7xapinb"},{"type":"text","value":"\n","position":{"start":{"line":5,"column":1},"end":{"line":5,"column":1}},"key":"YjA9HEdnrD"},{"type":"link","url":"https://doi.org/10.5281/zenodo.507993770","position":{"start":{"line":5,"column":1},"end":{"line":5,"column":1}},"children":[{"type":"image","url":"/cmip6-cookbook/build/a80787821e3725b2f599ac1acc21c3f7.svg","alt":"DOI","position":{"start":{"line":5,"column":1},"end":{"line":5,"column":1}},"key":"Z2q5sizaIW","urlSource":"https://zenodo.org/badge/507993770.svg"}],"urlSource":"https://zenodo.org/badge/latestdoi/507993770","data":{"doi":"10.5281/zenodo.507993770"},"internal":false,"protocol":"doi","key":"gAQeh42zzn"}],"key":"qCauA9nKS7"},{"type":"paragraph","position":{"start":{"line":9,"column":1},"end":{"line":9,"column":1}},"children":[{"type":"text","value":"This Project Pythia Cookbook covers examples of analysis of Google Cloud CMIP6 data using Pangeo tools.","position":{"start":{"line":9,"column":1},"end":{"line":9,"column":1}},"key":"QIwD9erlek"}],"key":"vNAIEFgPTg"},{"type":"heading","depth":2,"position":{"start":{"line":11,"column":1},"end":{"line":11,"column":1}},"children":[{"type":"text","value":"Motivation","position":{"start":{"line":11,"column":1},"end":{"line":11,"column":1}},"key":"HsOwsYbC1R"}],"identifier":"motivation","label":"Motivation","html_id":"motivation","implicit":true,"key":"X9ic5CWgT2"},{"type":"paragraph","position":{"start":{"line":13,"column":1},"end":{"line":13,"column":1}},"children":[{"type":"text","value":"From the ","position":{"start":{"line":13,"column":1},"end":{"line":13,"column":1}},"key":"Z4BCo49yLa"},{"type":"link","url":"https://esgf-node.llnl.gov/projects/cmip6/","position":{"start":{"line":13,"column":1},"end":{"line":13,"column":1}},"children":[{"type":"text","value":"CMIP6 website","position":{"start":{"line":13,"column":1},"end":{"line":13,"column":1}},"key":"UgmmQXFaJo"}],"urlSource":"https://esgf-node.llnl.gov/projects/cmip6/","key":"RSOpmEeHsu"},{"type":"text","value":":","position":{"start":{"line":13,"column":1},"end":{"line":13,"column":1}},"key":"onA3xZeveZ"}],"key":"SqzwxTnCsm"},{"type":"blockquote","position":{"start":{"line":15,"column":1},"end":{"line":15,"column":1}},"children":[{"type":"paragraph","position":{"start":{"line":15,"column":1},"end":{"line":15,"column":1}},"children":[{"type":"text","value":"The simulation data produced by models under previous phases of CMIP have been used in thousands of research papers ... and the multi-model results provide some perspective on errors and uncertainty in model simulations. This information has proved invaluable in preparing high profile reports assessing our understanding of climate and climate change (e.g., the IPCC Assessment Reports).","position":{"start":{"line":15,"column":1},"end":{"line":15,"column":1}},"key":"LPgYESfcDI"}],"key":"xXqTV8Gewv"}],"key":"e4h99J5nmQ"},{"type":"paragraph","position":{"start":{"line":17,"column":1},"end":{"line":17,"column":1}},"children":[{"type":"text","value":"With such a large amount of model output produced, moving the data around is inefficient. In this collection of notebooks, you will learn how to access cloud-optimized CMIP6 datasets, in addition to a few examples of using that data to analyze some aspects of climate change.","position":{"start":{"line":17,"column":1},"end":{"line":17,"column":1}},"key":"QBrrvgz1cH"}],"key":"cM5PuEVpUc"},{"type":"heading","depth":2,"position":{"start":{"line":19,"column":1},"end":{"line":19,"column":1}},"children":[{"type":"text","value":"Authors","position":{"start":{"line":19,"column":1},"end":{"line":19,"column":1}},"key":"UtY9DsAXBl"}],"identifier":"authors","label":"Authors","html_id":"authors","implicit":true,"key":"osEv14qaSb"},{"type":"paragraph","position":{"start":{"line":21,"column":1},"end":{"line":21,"column":1}},"children":[{"type":"link","url":"https://github.com/rabernat","position":{"start":{"line":21,"column":1},"end":{"line":21,"column":1}},"children":[{"type":"text","value":"Ryan Abernathey","position":{"start":{"line":21,"column":1},"end":{"line":21,"column":1}},"key":"dIhcEXodjp"}],"urlSource":"https://github.com/rabernat","error":true,"key":"nWjmEimIyx"},{"type":"text","value":", ","position":{"start":{"line":21,"column":1},"end":{"line":21,"column":1}},"key":"TB0wbPDhSf"},{"type":"link","url":"https://github.com/hdrake","position":{"start":{"line":21,"column":1},"end":{"line":21,"column":1}},"children":[{"type":"text","value":"Henri Drake","position":{"start":{"line":21,"column":1},"end":{"line":21,"column":1}},"key":"YPBVdXuj8R"}],"urlSource":"https://github.com/hdrake","error":true,"key":"WQo2myCXLA"},{"type":"text","value":", ","position":{"start":{"line":21,"column":1},"end":{"line":21,"column":1}},"key":"OyLXRKtft0"},{"type":"link","url":"https://github.com/r-ford","position":{"start":{"line":21,"column":1},"end":{"line":21,"column":1}},"children":[{"type":"text","value":"Robert Ford","position":{"start":{"line":21,"column":1},"end":{"line":21,"column":1}},"key":"jDifOEZCBn"}],"urlSource":"https://github.com/r-ford","error":true,"key":"pX4ahqtkW9"},{"type":"text","value":", ","position":{"start":{"line":21,"column":1},"end":{"line":21,"column":1}},"key":"TKbgFDPBwv"},{"type":"link","url":"https://github.com/mgrover1","position":{"start":{"line":21,"column":1},"end":{"line":21,"column":1}},"children":[{"type":"text","value":"Max Grover","position":{"start":{"line":21,"column":1},"end":{"line":21,"column":1}},"key":"qkLXsVi5jA"}],"urlSource":"https://github.com/mgrover1","error":true,"key":"dKKSAz79VA"}],"key":"xSbflK1Orc"},{"type":"heading","depth":3,"position":{"start":{"line":23,"column":1},"end":{"line":23,"column":1}},"children":[{"type":"text","value":"Contributors","position":{"start":{"line":23,"column":1},"end":{"line":23,"column":1}},"key":"MldQOo7BRc"}],"identifier":"contributors","label":"Contributors","html_id":"contributors","implicit":true,"key":"fmBmS85duH"},{"type":"link","url":"https://github.com/ProjectPythia/cmip6-cookbook/graphs/contributors","children":[{"type":"image","url":"/cmip6-cookbook/build/de8a1afc435b16c992eaa4b7e707da19.svg","key":"OBv4egBsJv","urlSource":"https://contrib.rocks/image?repo=ProjectPythia/cmip6-cookbook"}],"urlSource":"https://github.com/ProjectPythia/cmip6-cookbook/graphs/contributors","error":true,"key":"FvBWtSzrOX"},{"type":"heading","depth":2,"position":{"start":{"line":29,"column":1},"end":{"line":29,"column":1}},"children":[{"type":"text","value":"Structure","position":{"start":{"line":29,"column":1},"end":{"line":29,"column":1}},"key":"LzKZsByxWu"}],"identifier":"structure","label":"Structure","html_id":"structure","implicit":true,"key":"u8Ppk7k5jE"},{"type":"heading","depth":3,"position":{"start":{"line":31,"column":1},"end":{"line":31,"column":1}},"children":[{"type":"text","value":"Foundations","position":{"start":{"line":31,"column":1},"end":{"line":31,"column":1}},"key":"psdAGaBvc8"}],"identifier":"foundations","label":"Foundations","html_id":"foundations","implicit":true,"key":"kTYiKeT4xc"},{"type":"paragraph","position":{"start":{"line":33,"column":1},"end":{"line":33,"column":1}},"children":[{"type":"text","value":"This section includes three variations of accessing CMIP6 data from cloud storage.","position":{"start":{"line":33,"column":1},"end":{"line":33,"column":1}},"key":"xuzVrBZYef"}],"key":"trKkNL9lKt"},{"type":"heading","depth":3,"position":{"start":{"line":35,"column":1},"end":{"line":35,"column":1}},"children":[{"type":"text","value":"Example workflows","position":{"start":{"line":35,"column":1},"end":{"line":35,"column":1}},"key":"Ot9fBj5F9X"}],"identifier":"example-workflows","label":"Example workflows","html_id":"example-workflows","implicit":true,"key":"JBBRXPr3Zj"},{"type":"paragraph","position":{"start":{"line":37,"column":1},"end":{"line":37,"column":1}},"children":[{"type":"text","value":"There are currently four examples of using this data to","position":{"start":{"line":37,"column":1},"end":{"line":37,"column":1}},"key":"xzwZrwl2CE"}],"key":"xpNRgJIjEC"},{"type":"list","ordered":false,"spread":false,"position":{"start":{"line":38,"column":1},"end":{"line":42,"column":1}},"children":[{"type":"listItem","spread":true,"position":{"start":{"line":38,"column":1},"end":{"line":38,"column":1}},"children":[{"type":"paragraph","children":[{"type":"text","value":"Estimate equilibrium climate sensitivity (ECS)","position":{"start":{"line":38,"column":1},"end":{"line":38,"column":1}},"key":"XBdLrx1Pwn"}],"key":"uZtGODA02j"}],"key":"VU9LTwFrF4"},{"type":"listItem","spread":true,"position":{"start":{"line":39,"column":1},"end":{"line":39,"column":1}},"children":[{"type":"paragraph","children":[{"type":"text","value":"Plot global mean surface temperature under two different ","position":{"start":{"line":39,"column":1},"end":{"line":39,"column":1}},"key":"R5TQWwrABU"},{"type":"link","url":"https://unece.org/fileadmin/DAM/energy/se/pdfs/CSE/PATHWAYS/2019/ws_Consult_14_15.May.2019/supp_doc/SSP2_Overview.pdf","position":{"start":{"line":39,"column":1},"end":{"line":39,"column":1}},"children":[{"type":"text","value":"Shared Socioeconomic Pathways","position":{"start":{"line":39,"column":1},"end":{"line":39,"column":1}},"key":"g1NUW9QegC"}],"urlSource":"https://unece.org/fileadmin/DAM/energy/se/pdfs/CSE/PATHWAYS/2019/ws_Consult_14_15.May.2019/supp_doc/SSP2_Overview.pdf","key":"Az0CEFXFBA"}],"key":"yoYkmBOe38"}],"key":"isK6wvNmBX"},{"type":"listItem","spread":true,"position":{"start":{"line":40,"column":1},"end":{"line":40,"column":1}},"children":[{"type":"paragraph","children":[{"type":"text","value":"Plot changes in precipitation intensity under the SSP585 scenario","position":{"start":{"line":40,"column":1},"end":{"line":40,"column":1}},"key":"PUIY8RuGNU"}],"key":"pipwsaHwgr"}],"key":"sSpWo4CJof"},{"type":"listItem","spread":true,"position":{"start":{"line":41,"column":1},"end":{"line":42,"column":1}},"children":[{"type":"paragraph","children":[{"type":"text","value":"Calculate changes in ocean heat uptake after regridding with xESMF","position":{"start":{"line":41,"column":1},"end":{"line":41,"column":1}},"key":"qIPff1jROk"}],"key":"ySjkskMXB9"}],"key":"mJSkBXWKPn"}],"key":"Iu91lRyANa"},{"type":"heading","depth":2,"position":{"start":{"line":43,"column":1},"end":{"line":43,"column":1}},"children":[{"type":"text","value":"Running the Notebooks","position":{"start":{"line":43,"column":1},"end":{"line":43,"column":1}},"key":"ulbvai0YoT"}],"identifier":"running-the-notebooks","label":"Running the Notebooks","html_id":"running-the-notebooks","implicit":true,"key":"l1BVR51lHJ"},{"type":"paragraph","position":{"start":{"line":44,"column":1},"end":{"line":44,"column":1}},"children":[{"type":"text","value":"You can either run the notebook using ","position":{"start":{"line":44,"column":1},"end":{"line":44,"column":1}},"key":"kNqkFQcQrA"},{"type":"link","url":"https://binder.projectpythia.org","position":{"start":{"line":44,"column":1},"end":{"line":44,"column":1}},"children":[{"type":"text","value":"Binder","position":{"start":{"line":44,"column":1},"end":{"line":44,"column":1}},"key":"GBvvBEFSxS"}],"urlSource":"https://binder.projectpythia.org","key":"lMx9ygtwta"},{"type":"text","value":" or on your local machine.","position":{"start":{"line":44,"column":1},"end":{"line":44,"column":1}},"key":"DoayTgnkc1"}],"key":"oo8NLl2huK"},{"type":"heading","depth":3,"position":{"start":{"line":46,"column":1},"end":{"line":46,"column":1}},"children":[{"type":"text","value":"Running on Binder","position":{"start":{"line":46,"column":1},"end":{"line":46,"column":1}},"key":"VP9hVSKaG5"}],"identifier":"running-on-binder","label":"Running on Binder","html_id":"running-on-binder","implicit":true,"key":"EUOOITLVOl"},{"type":"paragraph","position":{"start":{"line":48,"column":1},"end":{"line":61,"column":1}},"children":[{"type":"text","value":"The simplest way to interact with a Jupyter Notebook is through\n","position":{"start":{"line":48,"column":1},"end":{"line":48,"column":1}},"key":"A1iuAo8ypy"},{"type":"link","url":"https://binder.projectpythia.org","position":{"start":{"line":48,"column":1},"end":{"line":48,"column":1}},"children":[{"type":"text","value":"Binder","position":{"start":{"line":48,"column":1},"end":{"line":48,"column":1}},"key":"hWykcfXsID"}],"urlSource":"https://binder.projectpythia.org","key":"JpDvaZ2aGR"},{"type":"text","value":", which enables the execution of a\n","position":{"start":{"line":48,"column":1},"end":{"line":48,"column":1}},"key":"aIbnf5sjGp"},{"type":"link","url":"https://jupyterbook.org","position":{"start":{"line":48,"column":1},"end":{"line":48,"column":1}},"children":[{"type":"text","value":"Jupyter Book","position":{"start":{"line":48,"column":1},"end":{"line":48,"column":1}},"key":"BeYJKGhvOv"}],"urlSource":"https://jupyterbook.org","key":"EUweqrChD4"},{"type":"text","value":" in the cloud. The details of how this works are not\nimportant for now. All you need to know is how to launch a Pythia\nCookbooks chapter via Binder. Simply navigate your mouse to\nthe top right corner of the book chapter you are viewing and click\non the rocket ship icon, (see figure below), and be sure to select\n“launch Binder”. After a moment you should be presented with a\nnotebook that you can interact with. I.e. you’ll be able to execute\nand even change the example programs. You’ll see that the code cells\nhave no output at first, until you execute them by pressing\n","position":{"start":{"line":48,"column":1},"end":{"line":48,"column":1}},"key":"jAEZ4yWiKj"},{"type":"keyboard","children":[{"type":"text","value":"Shift","key":"PPS7ZcsZ3X"}],"key":"bo3oIOeSx0"},{"type":"text","value":"+","position":{"start":{"line":48,"column":1},"end":{"line":48,"column":1}},"key":"eLRL8qDTsI"},{"type":"keyboard","children":[{"type":"text","value":"Enter","key":"lenC1nggqr"}],"key":"D4kozWwtyM"},{"type":"text","value":". Complete details on how to interact with\na live Jupyter notebook are described in ","position":{"start":{"line":48,"column":1},"end":{"line":48,"column":1}},"key":"LSpsltjXjy"},{"type":"link","url":"https://foundations.projectpythia.org/foundations/getting-started-jupyter","position":{"start":{"line":48,"column":1},"end":{"line":48,"column":1}},"children":[{"type":"text","value":"Getting Started with\nJupyter","position":{"start":{"line":48,"column":1},"end":{"line":48,"column":1}},"key":"zbV7djlG38"}],"urlSource":"https://foundations.projectpythia.org/foundations/getting-started-jupyter","key":"dWefShmIjY"},{"type":"text","value":".","position":{"start":{"line":48,"column":1},"end":{"line":48,"column":1}},"key":"s6joFu2LRX"}],"key":"Nvw0fUqmm7"},{"type":"heading","depth":3,"position":{"start":{"line":63,"column":1},"end":{"line":63,"column":1}},"children":[{"type":"text","value":"Running on Your Own Machine","position":{"start":{"line":63,"column":1},"end":{"line":63,"column":1}},"key":"Fd588eBUnO"}],"identifier":"running-on-your-own-machine","label":"Running on Your Own Machine","html_id":"running-on-your-own-machine","implicit":true,"key":"kgOUsEewYB"},{"type":"paragraph","position":{"start":{"line":64,"column":1},"end":{"line":64,"column":1}},"children":[{"type":"text","value":"If you are interested in running this material locally on your computer, you will need to follow this workflow:","position":{"start":{"line":64,"column":1},"end":{"line":64,"column":1}},"key":"l8DKRfLaGW"}],"key":"WgFu0XL4EW"},{"type":"list","ordered":true,"start":1,"spread":false,"position":{"start":{"line":66,"column":1},"end":{"line":85,"column":1}},"children":[{"type":"listItem","spread":true,"position":{"start":{"line":66,"column":1},"end":{"line":70,"column":1}},"children":[{"type":"paragraph","position":{"start":{"line":66,"column":1},"end":{"line":66,"column":1}},"children":[{"type":"text","value":"Clone the ","position":{"start":{"line":66,"column":1},"end":{"line":66,"column":1}},"key":"fIcZkY1Obd"},{"type":"inlineCode","value":"https://github.com/ProjectPythia/cmip6-cookbook","position":{"start":{"line":66,"column":1},"end":{"line":66,"column":1}},"key":"naRmakdyJ1"},{"type":"text","value":" repository:","position":{"start":{"line":66,"column":1},"end":{"line":66,"column":1}},"key":"ao6PQPC4Zv"}],"key":"VLCQpRlVpm"},{"type":"code","lang":"bash","value":" git clone https://github.com/ProjectPythia/cmip6-cookbook.git","position":{"start":{"line":68,"column":1},"end":{"line":70,"column":1}},"key":"uGtXFKHrt4"}],"key":"yrdu40ao33"},{"type":"listItem","spread":true,"position":{"start":{"line":71,"column":1},"end":{"line":74,"column":1}},"children":[{"type":"paragraph","position":{"start":{"line":71,"column":1},"end":{"line":71,"column":1}},"children":[{"type":"text","value":"Move into the ","position":{"start":{"line":71,"column":1},"end":{"line":71,"column":1}},"key":"lj0AP5KVkL"},{"type":"inlineCode","value":"cmip6-cookbook","position":{"start":{"line":71,"column":1},"end":{"line":71,"column":1}},"key":"qjvcIWKfcg"},{"type":"text","value":" directory","position":{"start":{"line":71,"column":1},"end":{"line":71,"column":1}},"key":"kxQ9wcPUKp"}],"key":"AwSz6KgByA"},{"type":"code","lang":"bash","value":"cd cmip6-cookbook","position":{"start":{"line":72,"column":1},"end":{"line":74,"column":1}},"key":"GZLmg18O60"}],"key":"gKurHM0nyx"},{"type":"listItem","spread":true,"position":{"start":{"line":75,"column":1},"end":{"line":79,"column":1}},"children":[{"type":"paragraph","position":{"start":{"line":75,"column":1},"end":{"line":75,"column":1}},"children":[{"type":"text","value":"Create and activate your conda environment from the ","position":{"start":{"line":75,"column":1},"end":{"line":75,"column":1}},"key":"rpVe0DhQPz"},{"type":"inlineCode","value":"environment.yml","position":{"start":{"line":75,"column":1},"end":{"line":75,"column":1}},"key":"TTUwJwv3Hq"},{"type":"text","value":" file","position":{"start":{"line":75,"column":1},"end":{"line":75,"column":1}},"key":"PaihCosFXw"}],"key":"kqjbo2MOX6"},{"type":"code","lang":"bash","value":"conda env create -f environment.yml\nconda activate cmip6-cookbook-dev","position":{"start":{"line":76,"column":1},"end":{"line":79,"column":1}},"key":"UyviQz2gTK"}],"key":"iqoaU8vwvV"},{"type":"listItem","spread":true,"position":{"start":{"line":80,"column":1},"end":{"line":85,"column":1}},"children":[{"type":"paragraph","position":{"start":{"line":80,"column":1},"end":{"line":80,"column":1}},"children":[{"type":"text","value":"Move into the ","position":{"start":{"line":80,"column":1},"end":{"line":80,"column":1}},"key":"E2VKr0ePAQ"},{"type":"inlineCode","value":"notebooks","position":{"start":{"line":80,"column":1},"end":{"line":80,"column":1}},"key":"S3PofxmHg9"},{"type":"text","value":" directory and start up Jupyterlab","position":{"start":{"line":80,"column":1},"end":{"line":80,"column":1}},"key":"G35ZIdejzj"}],"key":"GRdkFZaxEk"},{"type":"code","lang":"bash","value":"cd notebooks/\njupyter lab","position":{"start":{"line":81,"column":1},"end":{"line":84,"column":1}},"key":"advxJA9kIZ"}],"key":"nps12FKUqb"}],"key":"TRsN7g2adW"},{"type":"paragraph","position":{"start":{"line":86,"column":1},"end":{"line":86,"column":1}},"children":[{"type":"text","value":"At this point, you can interact with the notebooks! Make sure to check out the ","position":{"start":{"line":86,"column":1},"end":{"line":86,"column":1}},"key":"gB33N22YW2"},{"type":"link","url":"https://foundations.projectpythia.org/foundations/getting-started-jupyter","position":{"start":{"line":86,"column":1},"end":{"line":86,"column":1}},"children":[{"type":"text","value":"“Getting Started with Jupyter”","position":{"start":{"line":86,"column":1},"end":{"line":86,"column":1}},"key":"UGQJfQqe5y"}],"urlSource":"https://foundations.projectpythia.org/foundations/getting-started-jupyter","key":"cGS8aFOvCI"},{"type":"text","value":" content from the ","position":{"start":{"line":86,"column":1},"end":{"line":86,"column":1}},"key":"UOlFVgibGy"},{"type":"link","url":"https://foundations.projectpythia.org","position":{"start":{"line":86,"column":1},"end":{"line":86,"column":1}},"children":[{"type":"text","value":"Pythia Foundations","position":{"start":{"line":86,"column":1},"end":{"line":86,"column":1}},"key":"Nyzr0d9bt0"}],"urlSource":"https://foundations.projectpythia.org","key":"WhruQtm7lu"},{"type":"text","value":" material if you are new to Jupyter or need a refresher.","position":{"start":{"line":86,"column":1},"end":{"line":86,"column":1}},"key":"XXcpW0MJ0i"}],"key":"XbyyIFOxjr"}],"key":"bvbgP15hR3"}],"key":"GjmgBngdCm"},"references":{"cite":{"order":[],"data":{}}},"footer":{"navigation":{"next":{"title":"How to Cite This Cookbook","url":"/notebooks/how-to-cite","group":"Preamble"}}},"domain":"http://localhost:3000"}